mizdb_inlines/__init__.py
mizdb_inlines/renderers.py
mizdb_inlines/views.py
mizdb_inlines/static/mizdb_inlines/js/mizdb_inlines.js
mizdb_inlines/templates/mizdb_inlines/tabular_inline_formset.html
mizdb_inlines/templatetags/__init__.py
mizdb_inlines/templatetags/mizdb_inlines.py
mizdb_inlines-0.3.1.dist-info/LICENSE
mizdb_inlines-0.3.1.dist-info/METADATA
mizdb_inlines-0.3.1.dist-info/WHEEL
mizdb_inlines-0.3.1.dist-info/top_level.txt
mizdb_inlines-0.3.1.dist-info/RECORD
