Metadata-Version: 2.1
Name: mizdb-inlines
Version: 0.3.1
Summary: Django inline formsets with bootstrap
Author-email: Philip Becker <yummytea1@gmail.com>
Project-URL: Source, https://github.com/Actionb/mizdb-inlines
Classifier: Framework :: Django
Classifier: Programming Language :: Python :: 3
Requires-Python: >=3.8
License-File: LICENSE
Requires-Dist: Django
Requires-Dist: django-bootstrap5
